[
	{
		"officeFileAs": "Business Development",
		"officePrintAs": "Muller-Hudson",
		"email": "egarrett0@xrea.com",
		"website": "https://ucoz.com",
		"alias": "PH"
	},
	{
		"officeFileAs": "Training",
		"officePrintAs": "Welch, Hilpert and Ebert",
		"email": "ehanson1@cargocollective.com",
		"website": "https://phoca.cz",
		"alias": "PH"
	},
	{
		"officeFileAs": "Marketing",
		"officePrintAs": "O'Reilly, Adams and Yundt",
		"email": "efrazier2@ameblo.jp",
		"website": "http://macromedia.com",
		"alias": "PH"
	},
	{
		"officeFileAs": "Services",
		"officePrintAs": "Pfeffer-Dicki",
		"email": "emorales3@cnet.com",
		"website": "http://tuttocitta.it",
		"alias": "PT"
	},
	{
		"officeFileAs": "Business Development",
		"officePrintAs": "Pacocha and Sons",
		"email": "elopez4@netscape.com",
		"website": "https://cornell.edu",
		"alias": "FR"
	},
	{
		"officeFileAs": "Legal",
		"officePrintAs": "Feeney, Labadie and Prohaska",
		"email": "efuller5@weather.com",
		"website": "https://latimes.com",
		"alias": "PH"
	},
	{
		"officeFileAs": "Sales",
		"officePrintAs": "Reichel LLC",
		"email": "ereed6@google.pl",
		"website": "https://home.pl",
		"alias": "ME"
	},
	{
		"officeFileAs": "Support",
		"officePrintAs": "Littel-Kris",
		"email": "ewelch7@zdnet.com",
		"website": "http://devhub.com",
		"alias": "US"
	},
	{
		"officeFileAs": "Engineering",
		"officePrintAs": "Kemmer-Jerde",
		"email": "etorres8@unicef.org",
		"website": "https://ftc.gov",
		"alias": "ZA"
	},
	{
		"officeFileAs": "Legal",
		"officePrintAs": "Ondricka LLC",
		"email": "ehawkins9@wp.com",
		"website": "https://about.me",
		"alias": "BR"
	},
	{
		"officeFileAs": "Legal",
		"officePrintAs": "Yost and Sons",
		"email": "eandersona@cloudflare.com",
		"website": "https://ed.gov",
		"alias": "AL"
	},
	{
		"officeFileAs": "Services",
		"officePrintAs": "Schowalter-Ankunding",
		"email": "ebakerb@nydailynews.com",
		"website": "https://utexas.edu",
		"alias": "PH"
	},
	{
		"officeFileAs": "Engineering",
		"officePrintAs": "Kassulke, Kuphal and Kuphal",
		"email": "eellisc@ning.com",
		"website": "http://telegraph.co.uk",
		"alias": "PH"
	},
	{
		"officeFileAs": "Training",
		"officePrintAs": "Huel, Cronin and Hoppe",
		"email": "ereedd@cornell.edu",
		"website": "http://tripadvisor.com",
		"alias": "ZW"
	},
	{
		"officeFileAs": "Accounting",
		"officePrintAs": "Haag and Sons",
		"email": "eweavere@51.la",
		"website": "http://macromedia.com",
		"alias": "ID"
	},
	{
		"officeFileAs": "Legal",
		"officePrintAs": "Smitham, Fisher and Gerhold",
		"email": "ewestf@i2i.jp",
		"website": "http://ovh.net",
		"alias": "ID"
	},
	{
		"officeFileAs": "Research and Development",
		"officePrintAs": "Hahn LLC",
		"email": "ehowardg@edublogs.org",
		"website": "http://altervista.org",
		"alias": "PT"
	},
	{
		"officeFileAs": "Human Resources",
		"officePrintAs": "Greenfelder LLC",
		"email": "ediazh@imdb.com",
		"website": "http://vistaprint.com",
		"alias": "BR"
	},
	{
		"officeFileAs": "Support",
		"officePrintAs": "Koch-Kilback",
		"email": "epetersoni@goodreads.com",
		"website": "https://ow.ly",
		"alias": "SE"
	},
	{
		"officeFileAs": "Accounting",
		"officePrintAs": "Kunze and Sons",
		"email": "egrayj@acquirethisname.com",
		"website": "http://hatena.ne.jp",
		"alias": "ID"
	},
	{
		"officeFileAs": "Engineering",
		"officePrintAs": "Hirthe-Cartwright",
		"email": "esimmonsk@newsvine.com",
		"website": "https://zdnet.com",
		"alias": "ID"
	},
	{
		"officeFileAs": "Legal",
		"officePrintAs": "Moen-Walter",
		"email": "ebakerl@google.com.au",
		"website": "http://ox.ac.uk",
		"alias": "AL"
	},
	{
		"officeFileAs": "Engineering",
		"officePrintAs": "Fadel, Schuster and Lesch",
		"email": "ebarnesm@forbes.com",
		"website": "http://bbb.org",
		"alias": "BR"
	},
	{
		"officeFileAs": "Marketing",
		"officePrintAs": "Powlowski-Harvey",
		"email": "eallenn@g.co",
		"website": "http://salon.com",
		"alias": "BR"
	},
	{
		"officeFileAs": "Training",
		"officePrintAs": "Stroman LLC",
		"email": "ereyeso@tinypic.com",
		"website": "http://alibaba.com",
		"alias": "PH"
	},
	{
		"officeFileAs": "Product Management",
		"officePrintAs": "Dooley Inc",
		"email": "eoliverp@columbia.edu",
		"website": "http://soup.io",
		"alias": "US"
	},
	{
		"officeFileAs": "Business Development",
		"officePrintAs": "Mohr Group",
		"email": "eharveyq@last.fm",
		"website": "https://tmall.com",
		"alias": "ID"
	},
	{
		"officeFileAs": "Sales",
		"officePrintAs": "Kassulke-Stokes",
		"email": "eramirezr@deviantart.com",
		"website": "http://dell.com",
		"alias": "AR"
	},
	{
		"officeFileAs": "Research and Development",
		"officePrintAs": "Mitchell Group",
		"email": "egriffins@over-blog.com",
		"website": "https://nytimes.com",
		"alias": "CN"
	},
	{
		"officeFileAs": "Product Management",
		"officePrintAs": "Hessel-Erdman",
		"email": "ehughest@bravesites.com",
		"website": "https://51.la",
		"alias": "NO"
	},
	{
		"officeFileAs": "Training",
		"officePrintAs": "Schulist-Runolfsdottir",
		"email": "eknightu@blogspot.com",
		"website": "https://ycombinator.com",
		"alias": "SE"
	},
	{
		"officeFileAs": "Accounting",
		"officePrintAs": "Maggio Inc",
		"email": "egriffinv@alibaba.com",
		"website": "http://tuttocitta.it",
		"alias": "CZ"
	},
	{
		"officeFileAs": "Support",
		"officePrintAs": "Collins-Willms",
		"email": "egordonw@archive.org",
		"website": "https://fastcompany.com",
		"alias": "ID"
	},
	{
		"officeFileAs": "Product Management",
		"officePrintAs": "Mraz, D'Amore and Bradtke",
		"email": "esnyderx@nih.gov",
		"website": "http://w3.org",
		"alias": "JP"
	},
	{
		"officeFileAs": "Business Development",
		"officePrintAs": "Wiegand-Wolf",
		"email": "echavezy@nytimes.com",
		"website": "http://discuz.net",
		"alias": "RU"
	},
	{
		"officeFileAs": "Support",
		"officePrintAs": "Lowe, Welch and Bosco",
		"email": "eromeroz@java.com",
		"website": "http://usnews.com",
		"alias": "PK"
	},
	{
		"officeFileAs": "Sales",
		"officePrintAs": "Upton LLC",
		"email": "emorales10@disqus.com",
		"website": "https://trellian.com",
		"alias": "RU"
	},
	{
		"officeFileAs": "Research and Development",
		"officePrintAs": "Koepp LLC",
		"email": "ehill11@xing.com",
		"website": "http://unblog.fr",
		"alias": "ID"
	},
	{
		"officeFileAs": "Support",
		"officePrintAs": "Rau Inc",
		"email": "etucker12@cisco.com",
		"website": "https://paypal.com",
		"alias": "VE"
	},
	{
		"officeFileAs": "Marketing",
		"officePrintAs": "Hoppe, Schamberger and Zboncak",
		"email": "ewoods13@mapquest.com",
		"website": "https://patch.com",
		"alias": "TH"
	},
	{
		"officeFileAs": "Support",
		"officePrintAs": "Hickle and Sons",
		"email": "echapman14@wired.com",
		"website": "http://cbslocal.com",
		"alias": "PT"
	},
	{
		"officeFileAs": "Human Resources",
		"officePrintAs": "Mann, Abernathy and Homenick",
		"email": "eellis15@domainmarket.com",
		"website": "https://delicious.com",
		"alias": "CN"
	},
	{
		"officeFileAs": "Business Development",
		"officePrintAs": "Goldner, Lind and Kshlerin",
		"email": "ehart16@ow.ly",
		"website": "https://t.co",
		"alias": "ID"
	},
	{
		"officeFileAs": "Accounting",
		"officePrintAs": "Blanda-Stehr",
		"email": "elane17@godaddy.com",
		"website": "https://nih.gov",
		"alias": "PS"
	},
	{
		"officeFileAs": "Services",
		"officePrintAs": "Ullrich-Bergnaum",
		"email": "edunn18@yale.edu",
		"website": "http://guardian.co.uk",
		"alias": "CO"
	},
	{
		"officeFileAs": "Engineering",
		"officePrintAs": "Greenholt Inc",
		"email": "egilbert19@delicious.com",
		"website": "https://joomla.org",
		"alias": "MY"
	}
]